odoo/addons/account_statement_import_online_wise/README.rst
odoo/addons/account_statement_import_online_wise/__init__.py
odoo/addons/account_statement_import_online_wise/__manifest__.py
odoo/addons/account_statement_import_online_wise/i18n/account_bank_statement_import_online_transferwise.pot
odoo/addons/account_statement_import_online_wise/i18n/account_statement_import_online_wise.pot
odoo/addons/account_statement_import_online_wise/i18n/it.po
odoo/addons/account_statement_import_online_wise/i18n/nl.po
odoo/addons/account_statement_import_online_wise/models/__init__.py
odoo/addons/account_statement_import_online_wise/models/online_bank_statement_provider_transferwise.py
odoo/addons/account_statement_import_online_wise/readme/CONFIGURE.rst
odoo/addons/account_statement_import_online_wise/readme/CONTRIBUTORS.rst
odoo/addons/account_statement_import_online_wise/readme/DESCRIPTION.rst
odoo/addons/account_statement_import_online_wise/readme/USAGE.rst
odoo/addons/account_statement_import_online_wise/static/description/icon.png
odoo/addons/account_statement_import_online_wise/static/description/index.html
odoo/addons/account_statement_import_online_wise/tests/__init__.py
odoo/addons/account_statement_import_online_wise/tests/test_account_bank_statement_import_online_transferwise.py
odoo/addons/account_statement_import_online_wise/tests/test_account_statement_import_online_transferwise.py
odoo/addons/account_statement_import_online_wise/views/online_bank_statement_provider.xml
odoo14_addon_account_statement_import_online_wise-14.0.1.0.1.dist-info/METADATA
odoo14_addon_account_statement_import_online_wise-14.0.1.0.1.dist-info/WHEEL
odoo14_addon_account_statement_import_online_wise-14.0.1.0.1.dist-info/top_level.txt
odoo14_addon_account_statement_import_online_wise-14.0.1.0.1.dist-info/RECORD
